Workbook

Sheet Cahier
A1: Date | B1: Libellé | C1: Catégorie | D1: Entrée | E1: Sortie | F1: Moyen | G1: Solde espèces | H1: Solde Mobile Money
B2: Solde de départ | G2: 0 | H2: 0
G3: =IF(AND($D3="",$E3=""),"",$G$2+SUMIF($F$3:$F3,"Espèces",$D$3:$D3)-SUMIF($F$3:$F3,"Espèces",$E$3:$E3)) | H3: =IF(AND($D3="",$E3=""),"",$H$2+SUMIF($F$3:$F3,"Mobile Money",$D$3:$D3)-SUMIF($F$3:$F3,"Mobile Money",$E$3:$E3))
G4: =IF(AND($D4="",$E4=""),"",$G$2+SUMIF($F$3:$F4,"Espèces",$D$3:$D4)-SUMIF($F$3:$F4,"Espèces",$E$3:$E4)) | H4: =IF(AND($D4="",$E4=""),"",$H$2+SUMIF($F$3:$F4,"Mobile Money",$D$3:$D4)-SUMIF($F$3:$F4,"Mobile Money",$E$3:$E4))
G5: =IF(AND($D5="",$E5=""),"",$G$2+SUMIF($F$3:$F5,"Espèces",$D$3:$D5)-SUMIF($F$3:$F5,"Espèces",$E$3:$E5)) | H5: =IF(AND($D5="",$E5=""),"",$H$2+SUMIF($F$3:$F5,"Mobile Money",$D$3:$D5)-SUMIF($F$3:$F5,"Mobile Money",$E$3:$E5))
G6: =IF(AND($D6="",$E6=""),"",$G$2+SUMIF($F$3:$F6,"Espèces",$D$3:$D6)-SUMIF($F$3:$F6,"Espèces",$E$3:$E6)) | H6: =IF(AND($D6="",$E6=""),"",$H$2+SUMIF($F$3:$F6,"Mobile Money",$D$3:$D6)-SUMIF($F$3:$F6,"Mobile Money",$E$3:$E6))
G7: =IF(AND($D7="",$E7=""),"",$G$2+SUMIF($F$3:$F7,"Espèces",$D$3:$D7)-SUMIF($F$3:$F7,"Espèces",$E$3:$E7)) | H7: =IF(AND($D7="",$E7=""),"",$H$2+SUMIF($F$3:$F7,"Mobile Money",$D$3:$D7)-SUMIF($F$3:$F7,"Mobile Money",$E$3:$E7))
G8: =IF(AND($D8="",$E8=""),"",$G$2+SUMIF($F$3:$F8,"Espèces",$D$3:$D8)-SUMIF($F$3:$F8,"Espèces",$E$3:$E8)) | H8: =IF(AND($D8="",$E8=""),"",$H$2+SUMIF($F$3:$F8,"Mobile Money",$D$3:$D8)-SUMIF($F$3:$F8,"Mobile Money",$E$3:$E8))
G9: =IF(AND($D9="",$E9=""),"",$G$2+SUMIF($F$3:$F9,"Espèces",$D$3:$D9)-SUMIF($F$3:$F9,"Espèces",$E$3:$E9)) | H9: =IF(AND($D9="",$E9=""),"",$H$2+SUMIF($F$3:$F9,"Mobile Money",$D$3:$D9)-SUMIF($F$3:$F9,"Mobile Money",$E$3:$E9))
G10: =IF(AND($D10="",$E10=""),"",$G$2+SUMIF($F$3:$F10,"Espèces",$D$3:$D10)-SUMIF($F$3:$F10,"Espèces",$E$3:$E10)) | H10: =IF(AND($D10="",$E10=""),"",$H$2+SUMIF($F$3:$F10,"Mobile Money",$D$3:$D10)-SUMIF($F$3:$F10,"Mobile Money",$E$3:$E10))
G11: =IF(AND($D11="",$E11=""),"",$G$2+SUMIF($F$3:$F11,"Espèces",$D$3:$D11)-SUMIF($F$3:$F11,"Espèces",$E$3:$E11)) | H11: =IF(AND($D11="",$E11=""),"",$H$2+SUMIF($F$3:$F11,"Mobile Money",$D$3:$D11)-SUMIF($F$3:$F11,"Mobile Money",$E$3:$E11))
G12: =IF(AND($D12="",$E12=""),"",$G$2+SUMIF($F$3:$F12,"Espèces",$D$3:$D12)-SUMIF($F$3:$F12,"Espèces",$E$3:$E12)) | H12: =IF(AND($D12="",$E12=""),"",$H$2+SUMIF($F$3:$F12,"Mobile Money",$D$3:$D12)-SUMIF($F$3:$F12,"Mobile Money",$E$3:$E12))
G13: =IF(AND($D13="",$E13=""),"",$G$2+SUMIF($F$3:$F13,"Espèces",$D$3:$D13)-SUMIF($F$3:$F13,"Espèces",$E$3:$E13)) | H13: =IF(AND($D13="",$E13=""),"",$H$2+SUMIF($F$3:$F13,"Mobile Money",$D$3:$D13)-SUMIF($F$3:$F13,"Mobile Money",$E$3:$E13))
G14: =IF(AND($D14="",$E14=""),"",$G$2+SUMIF($F$3:$F14,"Espèces",$D$3:$D14)-SUMIF($F$3:$F14,"Espèces",$E$3:$E14)) | H14: =IF(AND($D14="",$E14=""),"",$H$2+SUMIF($F$3:$F14,"Mobile Money",$D$3:$D14)-SUMIF($F$3:$F14,"Mobile Money",$E$3:$E14))
... G502: =IF(AND($D502="",$E502=""),"",$G$2+SUMIF($F$3:$F502,"Espèces",$D$3:$D502)-SUMIF($F$3:$F502,"Espèces",$E$3:$E502)) | H502: =IF(AND($D502="",$E502=""),"",$H$2+SUMIF($F$3:$F502,"Mobile Money",$D$3:$D502)-SUMIF($F$3:$F502,"Mobile Money",$E$3:$E502))

Sheet Mois
A1: Le mois en chiffres
A3: Mois à regarder | D3: Écrivez le 1er jour du mois, par exemple 01/10/2026. Laissez vide pour voir tout le cahier.
A5: Total des entrées | B5: =IF($B$3="",SUM(Cahier!$D$3:$D$502),SUMIFS(Cahier!$D$3:$D$502,Cahier!$A$3:$A$502,">="&$B$3,Cahier!$A$3:$A$502,"<"&EDATE($B$3,1)))-B19 -> 0 | D5: Hors dépôts et retraits de Mobile Money : ce sont des déplacements d'argent, pas des ventes ni des dépenses.
A6: Total des sorties | B6: =IF($B$3="",SUM(Cahier!$E$3:$E$502),SUMIFS(Cahier!$E$3:$E$502,Cahier!$A$3:$A$502,">="&$B$3,Cahier!$A$3:$A$502,"<"&EDATE($B$3,1)))-C19 -> 0
A7: Résultat | B7: =B5-B6 -> 0
A10: Catégorie | B10: Entrées | C10: Sorties
A11: Vente | B11: =IF($B$3="",SUMIF(Cahier!$C$3:$C$502,$A11,Cahier!$D$3:$D$502),SUMIFS(Cahier!$D$3:$D$502,Cahier!$C$3:$C$502,$A11,Cahier!$A$3:$A$502,">="&$B$3,Cahier!$A$3:$A$502,"<"&EDATE($B$3,1))) -> 0 | C11: =IF($B$3="",SUMIF(Cahier!$C$3:$C$502,$A11,Cahier!$E$3:$E$502),SUMIFS(Cahier!$E$3:$E$502,Cahier!$C$3:$C$502,$A11,Cahier!$A$3:$A$502,">="&$B$3,Cahier!$A$3:$A$502,"<"&EDATE($B$3,1))) -> 0
A12: Avance reçue | B12: =IF($B$3="",SUMIF(Cahier!$C$3:$C$502,$A12,Cahier!$D$3:$D$502),SUMIFS(Cahier!$D$3:$D$502,Cahier!$C$3:$C$502,$A12,Cahier!$A$3:$A$502,">="&$B$3,Cahier!$A$3:$A$502,"<"&EDATE($B$3,1))) -> 0 | C12: =IF($B$3="",SUMIF(Cahier!$C$3:$C$502,$A12,Cahier!$E$3:$E$502),SUMIFS(Cahier!$E$3:$E$502,Cahier!$C$3:$C$502,$A12,Cahier!$A$3:$A$502,">="&$B$3,Cahier!$A$3:$A$502,"<"&EDATE($B$3,1))) -> 0
A13: Achat de marchandise | B13: =IF($B$3="",SUMIF(Cahier!$C$3:$C$502,$A13,Cahier!$D$3:$D$502),SUMIFS(Cahier!$D$3:$D$502,Cahier!$C$3:$C$502,$A13,Cahier!$A$3:$A$502,">="&$B$3,Cahier!$A$3:$A$502,"<"&EDATE($B$3,1))) -> 0 | C13: =IF($B$3="",SUMIF(Cahier!$C$3:$C$502,$A13,Cahier!$E$3:$E$502),SUMIFS(Cahier!$E$3:$E$502,Cahier!$C$3:$C$502,$A13,Cahier!$A$3:$A$502,">="&$B$3,Cahier!$A$3:$A$502,"<"&EDATE($B$3,1))) -> 0
A14: Transport et livraison | B14: =IF($B$3="",SUMIF(Cahier!$C$3:$C$502,$A14,Cahier!$D$3:$D$502),SUMIFS(Cahier!$D$3:$D$502,Cahier!$C$3:$C$502,$A14,Cahier!$A$3:$A$502,">="&$B$3,Cahier!$A$3:$A$502,"<"&EDATE($B$3,1))) -> 0 | C14: =IF($B$3="",SUMIF(Cahier!$C$3:$C$502,$A14,Cahier!$E$3:$E$502),SUMIFS(Cahier!$E$3:$E$502,Cahier!$C$3:$C$502,$A14,Cahier!$A$3:$A$502,">="&$B$3,Cahier!$A$3:$A$502,"<"&EDATE($B$3,1))) -> 0
A15: Loyer | B15: =IF($B$3="",SUMIF(Cahier!$C$3:$C$502,$A15,Cahier!$D$3:$D$502),SUMIFS(Cahier!$D$3:$D$502,Cahier!$C$3:$C$502,$A15,Cahier!$A$3:$A$502,">="&$B$3,Cahier!$A$3:$A$502,"<"&EDATE($B$3,1))) -> 0 | C15: =IF($B$3="",SUMIF(Cahier!$C$3:$C$502,$A15,Cahier!$E$3:$E$502),SUMIFS(Cahier!$E$3:$E$502,Cahier!$C$3:$C$502,$A15,Cahier!$A$3:$A$502,">="&$B$3,Cahier!$A$3:$A$502,"<"&EDATE($B$3,1))) -> 0
A16: Connexion et crédit téléphonique | B16: =IF($B$3="",SUMIF(Cahier!$C$3:$C$502,$A16,Cahier!$D$3:$D$502),SUMIFS(Cahier!$D$3:$D$502,Cahier!$C$3:$C$502,$A16,Cahier!$A$3:$A$502,">="&$B$3,Cahier!$A$3:$A$502,"<"&EDATE($B$3,1))) -> 0 | C16: =IF($B$3="",SUMIF(Cahier!$C$3:$C$502,$A16,Cahier!$E$3:$E$502),SUMIFS(Cahier!$E$3:$E$502,Cahier!$C$3:$C$502,$A16,Cahier!$A$3:$A$502,">="&$B$3,Cahier!$A$3:$A$502,"<"&EDATE($B$3,1))) -> 0
A17: Salaire | B17: =IF($B$3="",SUMIF(Cahier!$C$3:$C$502,$A17,Cahier!$D$3:$D$502),SUMIFS(Cahier!$D$3:$D$502,Cahier!$C$3:$C$502,$A17,Cahier!$A$3:$A$502,">="&$B$3,Cahier!$A$3:$A$502,"<"&EDATE($B$3,1))) -> 0 | C17: =IF($B$3="",SUMIF(Cahier!$C$3:$C$502,$A17,Cahier!$E$3:$E$502),SUMIFS(Cahier!$E$3:$E$502,Cahier!$C$3:$C$502,$A17,Cahier!$A$3:$A$502,">="&$B$3,Cahier!$A$3:$A$502,"<"&EDATE($B$3,1))) -> 0
A18: Pris pour la maison | B18: =IF($B$3="",SUMIF(Cahier!$C$3:$C$502,$A18,Cahier!$D$3:$D$502),SUMIFS(Cahier!$D$3:$D$502,Cahier!$C$3:$C$502,$A18,Cahier!$A$3:$A$502,">="&$B$3,Cahier!$A$3:$A$502,"<"&EDATE($B$3,1))) -> 0 | C18: =IF($B$3="",SUMIF(Cahier!$C$3:$C$502,$A18,Cahier!$E$3:$E$502),SUMIFS(Cahier!$E$3:$E$502,Cahier!$C$3:$C$502,$A18,Cahier!$A$3:$A$502,">="&$B$3,Cahier!$A$3:$A$502,"<"&EDATE($B$3,1))) -> 0
A19: Dépôt ou retrait de Mobile Money | B19: =IF($B$3="",SUMIF(Cahier!$C$3:$C$502,$A19,Cahier!$D$3:$D$502),SUMIFS(Cahier!$D$3:$D$502,Cahier!$C$3:$C$502,$A19,Cahier!$A$3:$A$502,">="&$B$3,Cahier!$A$3:$A$502,"<"&EDATE($B$3,1))) -> 0 | C19: =IF($B$3="",SUMIF(Cahier!$C$3:$C$502,$A19,Cahier!$E$3:$E$502),SUMIFS(Cahier!$E$3:$E$502,Cahier!$C$3:$C$502,$A19,Cahier!$A$3:$A$502,">="&$B$3,Cahier!$A$3:$A$502,"<"&EDATE($B$3,1))) -> 0
A20: Écart de caisse | B20: =IF($B$3="",SUMIF(Cahier!$C$3:$C$502,$A20,Cahier!$D$3:$D$502),SUMIFS(Cahier!$D$3:$D$502,Cahier!$C$3:$C$502,$A20,Cahier!$A$3:$A$502,">="&$B$3,Cahier!$A$3:$A$502,"<"&EDATE($B$3,1))) -> 0 | C20: =IF($B$3="",SUMIF(Cahier!$C$3:$C$502,$A20,Cahier!$E$3:$E$502),SUMIFS(Cahier!$E$3:$E$502,Cahier!$C$3:$C$502,$A20,Cahier!$A$3:$A$502,">="&$B$3,Cahier!$A$3:$A$502,"<"&EDATE($B$3,1))) -> 0
A21: Autre | B21: =IF($B$3="",SUMIF(Cahier!$C$3:$C$502,$A21,Cahier!$D$3:$D$502),SUMIFS(Cahier!$D$3:$D$502,Cahier!$C$3:$C$502,$A21,Cahier!$A$3:$A$502,">="&$B$3,Cahier!$A$3:$A$502,"<"&EDATE($B$3,1))) -> 0 | C21: =IF($B$3="",SUMIF(Cahier!$C$3:$C$502,$A21,Cahier!$E$3:$E$502),SUMIFS(Cahier!$E$3:$E$502,Cahier!$C$3:$C$502,$A21,Cahier!$A$3:$A$502,">="&$B$3,Cahier!$A$3:$A$502,"<"&EDATE($B$3,1))) -> 0
A22: Sans catégorie | B22: =IF($B$3="",SUM(Cahier!$D$3:$D$502),SUMIFS(Cahier!$D$3:$D$502,Cahier!$A$3:$A$502,">="&$B$3,Cahier!$A$3:$A$502,"<"&EDATE($B$3,1)))-SUM(B11:B21) -> 0 | C22: =IF($B$3="",SUM(Cahier!$E$3:$E$502),SUMIFS(Cahier!$E$3:$E$502,Cahier!$A$3:$A$502,">="&$B$3,Cahier!$A$3:$A$502,"<"&EDATE($B$3,1)))-SUM(C11:C21) -> 0 | D22: Si cette ligne n'est pas à zéro, une opération du cahier n'a pas de catégorie.
A24: Entrées par moyen de paiement
A25: Moyen | B25: Entrées | C25: Part
A26: Espèces | B26: =IF($B$3="",SUMIF(Cahier!$F$3:$F$502,"Espèces",Cahier!$D$3:$D$502)-SUMIFS(Cahier!$D$3:$D$502,Cahier!$F$3:$F$502,"Espèces",Cahier!$C$3:$C$502,"Dépôt ou retrait de Mobile Money"),SUMIFS(Cahier!$D$3:$D$502,Cahier!$F$3:$F$502,"Espèces",Cahier!$A$3:$A$502,">="&$B$3,Cahier!$A$3:$A$502,"<"&EDATE($B$3,1))-SUMIFS(Cahier!$D$3:$D$502,Cahier!$F$3:$F$502,"Espèces",Cahier!$C$3:$C$502,"Dépôt ou retrait de Mobile Money",Cahier!$A$3:$A$502,">="&$B$3,Cahier!$A$3:$A$502,"<"&EDATE($B$3,1))) -> 0 | C26: =IF($B$5=0,"",B26/$B$5)
A27: Mobile Money | B27: =IF($B$3="",SUMIF(Cahier!$F$3:$F$502,"Mobile Money",Cahier!$D$3:$D$502)-SUMIFS(Cahier!$D$3:$D$502,Cahier!$F$3:$F$502,"Mobile Money",Cahier!$C$3:$C$502,"Dépôt ou retrait de Mobile Money"),SUMIFS(Cahier!$D$3:$D$502,Cahier!$F$3:$F$502,"Mobile Money",Cahier!$A$3:$A$502,">="&$B$3,Cahier!$A$3:$A$502,"<"&EDATE($B$3,1))-SUMIFS(Cahier!$D$3:$D$502,Cahier!$F$3:$F$502,"Mobile Money",Cahier!$C$3:$C$502,"Dépôt ou retrait de Mobile Money",Cahier!$A$3:$A$502,">="&$B$3,Cahier!$A$3:$A$502,"<"&EDATE($B$3,1))) -> 0 | C27: =IF($B$5=0,"",B27/$B$5)
A28: Moyen non précisé | B28: =$B$5-B26-B27 -> 0 | C28: =IF($B$5=0,"",B28/$B$5)

Sheet Mode d'emploi
A1: Cahier de caisse : mode d'emploi
A3: COMMENT REMPLIR :
A4: 1. Écrivez seulement dans les cases blanches et dans les cases jaunes. Les cases grises se calculent seules : n'y touchez pas.
A5: 2. Onglet Cahier, ligne 2 : écrivez l'argent que vous avez au départ. Dans la case jaune « Solde espèces », l'argent de la caisse. Dans la case jaune « Solde Mobile Money », l'argent de votre compte.
A6: 3. Ensuite, une opération par ligne. Entrée : l'argent reçu. Sortie : l'argent dépensé. Écrivez le montant en chiffres, sans le mot FCFA.
A7: 4. Choisissez toujours la catégorie et le moyen dans les listes. Si le moyen manque, la case devient rouge et les soldes ne bougent pas.
A8: 5. Si vous collez des lignes préparées par votre IA et qu'une date ou un montant devient rouge, retapez cette case : un montant en chiffres seulement (43000), une date sous la forme 05/10/2026.
A9: 6. Les deux soldes se mettent à jour à chaque ligne : ce qu'il doit y avoir dans la caisse, et ce qu'il doit y avoir sur le compte Mobile Money.
A11: CAS PARTICULIERS :
A12: Une avance reçue d'un client : une entrée, catégorie « Avance reçue ».
A13: De l'argent pris dans la caisse pour la maison : une sortie, catégorie « Pris pour la maison ».
A14: Un dépôt sur votre compte Mobile Money : deux lignes du même montant, catégorie « Dépôt ou retrait de Mobile Money ». Une sortie en Espèces, puis une entrée en Mobile Money. Pour un retrait, c'est l'inverse.
... A25: EXEMPLE (ne modifiez pas cet exemple, il sert seulement de modèle) :
A26: Date | B26: Libellé | C26: Catégorie | D26: Entrée | E26: Sortie | F26: Moyen | G26: Solde espèces | H26: Solde Mobile Money
B27: Solde de départ | G27: 15000 | H27: 40000
A28: 46300 | B28: Vente 2 pagnes | C28: Vente | D28: 43000 | F28: Espèces | G28: =$G$27+SUMIF($F$28:$F28,"Espèces",$D$28:$D28)-SUMIF($F$28:$F28,"Espèces",$E$28:$E28) -> 58000 | H28: =$H$27+SUMIF($F$28:$F28,"Mobile Money",$D$28:$D28)-SUMIF($F$28:$F28,"Mobile Money",$E$28:$E28) -> 40000
A29: 46300 | B29: Vente 1 pagne | C29: Vente | D29: 14000 | F29: Mobile Money | G29: =$G$27+SUMIF($F$28:$F29,"Espèces",$D$28:$D29)-SUMIF($F$28:$F29,"Espèces",$E$28:$E29) -> 58000 | H29: =$H$27+SUMIF($F$28:$F29,"Mobile Money",$D$28:$D29)-SUMIF($F$28:$F29,"Mobile Money",$E$28:$E29) -> 54000
A30: 46300 | B30: Avance sur un pagne | C30: Avance reçue | D30: 10000 | F30: Mobile Money | G30: =$G$27+SUMIF($F$28:$F30,"Espèces",$D$28:$D30)-SUMIF($F$28:$F30,"Espèces",$E$28:$E30) -> 58000 | H30: =$H$27+SUMIF($F$28:$F30,"Mobile Money",$D$28:$D30)-SUMIF($F$28:$F30,"Mobile Money",$E$28:$E30) -> 64000
A31: 46300 | B31: Taxi | C31: Transport et livraison | E31: 300 | F31: Espèces | G31: =$G$27+SUMIF($F$28:$F31,"Espèces",$D$28:$D31)-SUMIF($F$28:$F31,"Espèces",$E$28:$E31) -> 57700 | H31: =$H$27+SUMIF($F$28:$F31,"Mobile Money",$D$28:$D31)-SUMIF($F$28:$F31,"Mobile Money",$E$28:$E31) -> 64000
A32: 46300 | B32: Livraison à moto | C32: Transport et livraison | E32: 2000 | F32: Espèces | G32: =$G$27+SUMIF($F$28:$F32,"Espèces",$D$28:$D32)-SUMIF($F$28:$F32,"Espèces",$E$28:$E32) -> 55700 | H32: =$H$27+SUMIF($F$28:$F32,"Mobile Money",$D$28:$D32)-SUMIF($F$28:$F32,"Mobile Money",$E$28:$E32) -> 64000
A33: 46300 | B33: Forfait internet | C33: Connexion et crédit téléphonique | E33: 1000 | F33: Espèces | G33: =$G$27+SUMIF($F$28:$F33,"Espèces",$D$28:$D33)-SUMIF($F$28:$F33,"Espèces",$E$28:$E33) -> 54700 | H33: =$H$27+SUMIF($F$28:$F33,"Mobile Money",$D$28:$D33)-SUMIF($F$28:$F33,"Mobile Money",$E$28:$E33) -> 64000
A34: 46300 | B34: Pris pour la maison | C34: Pris pour la maison | E34: 5000 | F34: Espèces | G34: =$G$27+SUMIF($F$28:$F34,"Espèces",$D$28:$D34)-SUMIF($F$28:$F34,"Espèces",$E$28:$E34) -> 49700 | H34: =$H$27+SUMIF($F$28:$F34,"Mobile Money",$D$28:$D34)-SUMIF($F$28:$F34,"Mobile Money",$E$28:$E34) -> 64000
A36: À la fin de cette journée, il doit y avoir 49 700 FCFA dans la caisse et 64 000 FCFA sur le compte Mobile Money.
A38: Document du kit « Commerce et vente en ligne » d'AI WORK KIT.
