Workbook

Sheet Réglages
A1: Vos réglages
A3: Revenu mensuel que vous visez (FCFA) | C3: Ce que vous voulez gagner chaque mois, une fois vos charges payées.
A4: Charges du mois (FCFA) | C4: Connexion, logiciels, matériel, transport, loyer du local.
A5: Jours facturables par mois | C5: Les jours vraiment passés à créer pour un client. Pas les jours de démarchage.
A6: Heures de création par jour
A8: Coût d'une journée (FCFA) | B8: =IF(OR($B$3="",$B$5="",$B$5=0),"",ROUND(($B$3+$B$4)/$B$5,0))
A9: Coût d'une heure (FCFA) | B9: =IF(OR($B$8="",$B$6="",$B$6=0),"",ROUND($B$8/$B$6,0))

Sheet Prestations
A1: Prestation | B1: Temps passé (heures) | C1: Coût de votre temps (FCFA) | D1: Frais (FCFA) | E1: Prix plancher (FCFA) | F1: Votre prix affiché (FCFA) | G1: Écart (FCFA) | H1: Modifications comprises
C2: =IF(OR($B2="",Réglages!$B$9=""),"",ROUND($B2*Réglages!$B$9,0)) | E2: =IF($C2="","",$C2+$D2) | G2: =IF(OR($E2="",$F2=""),"",$F2-$E2)
C3: =IF(OR($B3="",Réglages!$B$9=""),"",ROUND($B3*Réglages!$B$9,0)) | E3: =IF($C3="","",$C3+$D3) | G3: =IF(OR($E3="",$F3=""),"",$F3-$E3)
C4: =IF(OR($B4="",Réglages!$B$9=""),"",ROUND($B4*Réglages!$B$9,0)) | E4: =IF($C4="","",$C4+$D4) | G4: =IF(OR($E4="",$F4=""),"",$F4-$E4)
C5: =IF(OR($B5="",Réglages!$B$9=""),"",ROUND($B5*Réglages!$B$9,0)) | E5: =IF($C5="","",$C5+$D5) | G5: =IF(OR($E5="",$F5=""),"",$F5-$E5)
C6: =IF(OR($B6="",Réglages!$B$9=""),"",ROUND($B6*Réglages!$B$9,0)) | E6: =IF($C6="","",$C6+$D6) | G6: =IF(OR($E6="",$F6=""),"",$F6-$E6)
C7: =IF(OR($B7="",Réglages!$B$9=""),"",ROUND($B7*Réglages!$B$9,0)) | E7: =IF($C7="","",$C7+$D7) | G7: =IF(OR($E7="",$F7=""),"",$F7-$E7)
C8: =IF(OR($B8="",Réglages!$B$9=""),"",ROUND($B8*Réglages!$B$9,0)) | E8: =IF($C8="","",$C8+$D8) | G8: =IF(OR($E8="",$F8=""),"",$F8-$E8)
C9: =IF(OR($B9="",Réglages!$B$9=""),"",ROUND($B9*Réglages!$B$9,0)) | E9: =IF($C9="","",$C9+$D9) | G9: =IF(OR($E9="",$F9=""),"",$F9-$E9)
C10: =IF(OR($B10="",Réglages!$B$9=""),"",ROUND($B10*Réglages!$B$9,0)) | E10: =IF($C10="","",$C10+$D10) | G10: =IF(OR($E10="",$F10=""),"",$F10-$E10)
C11: =IF(OR($B11="",Réglages!$B$9=""),"",ROUND($B11*Réglages!$B$9,0)) | E11: =IF($C11="","",$C11+$D11) | G11: =IF(OR($E11="",$F11=""),"",$F11-$E11)
C12: =IF(OR($B12="",Réglages!$B$9=""),"",ROUND($B12*Réglages!$B$9,0)) | E12: =IF($C12="","",$C12+$D12) | G12: =IF(OR($E12="",$F12=""),"",$F12-$E12)
C13: =IF(OR($B13="",Réglages!$B$9=""),"",ROUND($B13*Réglages!$B$9,0)) | E13: =IF($C13="","",$C13+$D13) | G13: =IF(OR($E13="",$F13=""),"",$F13-$E13)
... C101: =IF(OR($B101="",Réglages!$B$9=""),"",ROUND($B101*Réglages!$B$9,0)) | E101: =IF($C101="","",$C101+$D101) | G101: =IF(OR($E101="",$F101=""),"",$F101-$E101)

Sheet Résumé
A1: Vos prix en un coup d'œil
A3: Coût d'une journée (FCFA) | B3: =Réglages!$B$8
A4: Coût d'une heure (FCFA) | B4: =Réglages!$B$9
A5: Prestations | B5: =COUNTA(Prestations!$A$2:$A$101)
A6: Prestations vendues sous leur prix plancher | B6: =COUNTIF(Prestations!$G$2:$G$101,"<0")

Sheet Mode d'emploi
A1: Grille tarifaire : mode d'emploi
A3: COMMENT REMPLIR :
A4: 1. Onglet « Réglages » : écrivez dans les cases jaunes le revenu que vous visez, vos charges du mois, vos jours facturables et vos heures de création par jour. Le coût d'une journée et d'une heure se calcule seul.
A5: 2. Onglet « Prestations » : une ligne par prestation. Écrivez le temps que vous y passez vraiment, modifications comprises, et vos frais : impression d'essai, achat d'une image.
A6: 3. Le prix plancher se calcule seul : le coût de votre temps, plus vos frais. En dessous, vous travaillez à perte.
A7: 4. Écrivez le prix que vous affichez. L'écart s'affiche en rouge quand votre prix est sous le plancher.
A9: À SAVOIR :
A10: Tous les chiffres sont les vôtres : ce tableau ne connaît pas les prix du marché et ne dit pas ce que vos clients accepteront de payer. Il dit seulement ce que chaque prestation vous coûte.
A12: EXEMPLE (ne modifiez pas cet exemple, il sert seulement de modèle) :
A13: Réglages de l'exemple : 110 000 FCFA visés, 15 000 FCFA de charges, 20 jours facturables, 5 heures par jour. Coût d'une journée : 125 000 ÷ 20 = 6 250 FCFA. Coût d'une heure : 6 250 ÷ 5 = 1 250 FCFA.
A14: Prestation | B14: Temps passé (heures) | C14: Coût de votre temps (FCFA) | D14: Frais (FCFA) | E14: Prix plancher (FCFA) | F14: Votre prix affiché (FCFA) | G14: Écart (FCFA) | H14: Modifications comprises
A15: Logo | B15: 12 | C15: =B15*1250 | D15: 0 | E15: =C15+D15 | F15: 22500 | G15: =F15-E15 | H15: 2
A16: Affiche d'événement | B16: 3 | C16: =B16*1250 | D16: 0 | E16: =C16+D16 | F16: 4500 | G16: =F16-E16 | H16: 2
A18: Dans cet exemple : le logo demande 12 heures, soit 15 000 FCFA de temps. Affiché à 22 500 FCFA, il laisse 7 500 FCFA au-dessus du plancher. L'affiche demande 3 heures, soit 3 750 FCFA : affichée à 4 500 FCFA, elle laisse 750 FCFA.
A20: Document du kit « Graphisme » d'AI WORK KIT.
