Workbook

Sheet Campagnes
A1: Publicité ou campagne | B1: Réseau | C1: Début | D1: Fin | E1: Budget dépensé (FCFA) | F1: Personnes touchées | G1: Messages ou clics | H1: Nombre de ventes | I1: Montant des ventes (FCFA) | J1: Coût par message (FCFA) | K1: Coût par vente (FCFA) | L1: Ventes pour 1 FCFA dépensé | M1: Décision
J2: =IF(OR($E2="",$G2="",$G2=0),"",$E2/$G2) | K2: =IF(OR($E2="",$H2="",$H2=0),"",$E2/$H2) | L2: =IF(OR($E2="",$E2=0,$I2=""),"",$I2/$E2)
J3: =IF(OR($E3="",$G3="",$G3=0),"",$E3/$G3) | K3: =IF(OR($E3="",$H3="",$H3=0),"",$E3/$H3) | L3: =IF(OR($E3="",$E3=0,$I3=""),"",$I3/$E3)
J4: =IF(OR($E4="",$G4="",$G4=0),"",$E4/$G4) | K4: =IF(OR($E4="",$H4="",$H4=0),"",$E4/$H4) | L4: =IF(OR($E4="",$E4=0,$I4=""),"",$I4/$E4)
J5: =IF(OR($E5="",$G5="",$G5=0),"",$E5/$G5) | K5: =IF(OR($E5="",$H5="",$H5=0),"",$E5/$H5) | L5: =IF(OR($E5="",$E5=0,$I5=""),"",$I5/$E5)
J6: =IF(OR($E6="",$G6="",$G6=0),"",$E6/$G6) | K6: =IF(OR($E6="",$H6="",$H6=0),"",$E6/$H6) | L6: =IF(OR($E6="",$E6=0,$I6=""),"",$I6/$E6)
J7: =IF(OR($E7="",$G7="",$G7=0),"",$E7/$G7) | K7: =IF(OR($E7="",$H7="",$H7=0),"",$E7/$H7) | L7: =IF(OR($E7="",$E7=0,$I7=""),"",$I7/$E7)
J8: =IF(OR($E8="",$G8="",$G8=0),"",$E8/$G8) | K8: =IF(OR($E8="",$H8="",$H8=0),"",$E8/$H8) | L8: =IF(OR($E8="",$E8=0,$I8=""),"",$I8/$E8)
J9: =IF(OR($E9="",$G9="",$G9=0),"",$E9/$G9) | K9: =IF(OR($E9="",$H9="",$H9=0),"",$E9/$H9) | L9: =IF(OR($E9="",$E9=0,$I9=""),"",$I9/$E9)
J10: =IF(OR($E10="",$G10="",$G10=0),"",$E10/$G10) | K10: =IF(OR($E10="",$H10="",$H10=0),"",$E10/$H10) | L10: =IF(OR($E10="",$E10=0,$I10=""),"",$I10/$E10)
J11: =IF(OR($E11="",$G11="",$G11=0),"",$E11/$G11) | K11: =IF(OR($E11="",$H11="",$H11=0),"",$E11/$H11) | L11: =IF(OR($E11="",$E11=0,$I11=""),"",$I11/$E11)
J12: =IF(OR($E12="",$G12="",$G12=0),"",$E12/$G12) | K12: =IF(OR($E12="",$H12="",$H12=0),"",$E12/$H12) | L12: =IF(OR($E12="",$E12=0,$I12=""),"",$I12/$E12)
J13: =IF(OR($E13="",$G13="",$G13=0),"",$E13/$G13) | K13: =IF(OR($E13="",$H13="",$H13=0),"",$E13/$H13) | L13: =IF(OR($E13="",$E13=0,$I13=""),"",$I13/$E13)
... J201: =IF(OR($E201="",$G201="",$G201=0),"",$E201/$G201) | K201: =IF(OR($E201="",$H201="",$H201=0),"",$E201/$H201) | L201: =IF(OR($E201="",$E201=0,$I201=""),"",$I201/$E201)

Sheet Résumé
A1: Vos campagnes en un coup d'œil
A3: Publicités suivies | B3: =COUNTA(Campagnes!$A$2:$A$201)
A4: Total dépensé (FCFA) | B4: =SUM(Campagnes!$E$2:$E$201)
A5: Total des ventes (FCFA) | B5: =SUM(Campagnes!$I$2:$I$201)
A6: Messages ou clics reçus | B6: =SUM(Campagnes!$G$2:$G$201)
A7: Nombre de ventes | B7: =SUM(Campagnes!$H$2:$H$201)
A8: Coût moyen par message (FCFA) | B8: =IF(SUM(Campagnes!$G$2:$G$201)=0,"",SUM(Campagnes!$E$2:$E$201)/SUM(Campagnes!$G$2:$G$201))
A9: Coût moyen par vente (FCFA) | B9: =IF(SUM(Campagnes!$H$2:$H$201)=0,"",SUM(Campagnes!$E$2:$E$201)/SUM(Campagnes!$H$2:$H$201))
A10: Ventes pour 1 FCFA dépensé | B10: =IF(SUM(Campagnes!$E$2:$E$201)=0,"",SUM(Campagnes!$I$2:$I$201)/SUM(Campagnes!$E$2:$E$201))
A11: Publicités à garder | B11: =COUNTIF(Campagnes!$M$2:$M$201,"Garder")
A12: Publicités à arrêter | B12: =COUNTIF(Campagnes!$M$2:$M$201,"Arrêter")

Sheet Mode d'emploi
A1: Suivi des campagnes : mode d'emploi
A3: COMMENT REMPLIR :
A4: 1. Une ligne par publicité ou par campagne. Écrivez seulement dans les cases blanches : les trois cases grises se calculent seules.
A5: 2. Budget dépensé, personnes touchées, messages ou clics : recopiez les chiffres de votre gestionnaire de publicités.
A6: 3. Nombre de ventes et montant des ventes : comptez seulement les ventes réelles venues de cette publicité.
A7: 4. Écrivez les montants en chiffres, sans « FCFA » ni point : 21000. Dates sous la forme 05/10/2026. Une case rouge : retapez-la.
A8: 5. Décision : choisissez dans la liste. « Attendre » quand il y a trop peu de ventes pour conclure.
A10: LES TROIS CALCULS :
A11: Coût par message : le budget dépensé, divisé par le nombre de messages ou de clics.
A12: Coût par vente : le budget dépensé, divisé par le nombre de ventes.
A13: Ventes pour 1 FCFA dépensé : le montant des ventes, divisé par le budget. À 5,0, chaque franc dépensé a fait vendre pour 5 francs. Ce n'est pas votre bénéfice : le prix de revient n'est pas compté.
A15: À SAVOIR :
... A18: EXEMPLE (ne modifiez pas cet exemple, il sert seulement de modèle) :
A19: Publicité ou campagne | B19: Réseau | C19: Début | D19: Fin | E19: Budget dépensé (FCFA) | F19: Personnes touchées | G19: Messages ou clics | H19: Nombre de ventes | I19: Montant des ventes (FCFA) | J19: Coût par message (FCFA) | K19: Coût par vente (FCFA) | L19: Ventes pour 1 FCFA dépensé | M19: Décision
A20: A, la photo du plat | B20: Facebook | C20: 46300 | D20: 46306 | E20: 7000 | F20: 2400 | G20: 35 | H20: 14 | I20: 35000 | J20: =E20/G20 | K20: =E20/H20 | L20: =I20/E20 | M20: Garder
A21: B, la vidéo de la cuisine | B21: Facebook | C21: 46300 | D21: 46306 | E21: 7000 | F21: 5100 | G21: 70 | H21: 7 | I21: 17500 | J21: =E21/G21 | K21: =E21/H21 | L21: =I21/E21 | M21: Modifier
A23: Dans cet exemple : la publicité B reçoit deux fois plus de messages que la A, à 100 FCFA le message contre 200. Mais elle vend deux fois moins : 1 000 FCFA par vente contre 500. La conversation la moins chère n'est pas la meilleure publicité.
A25: Document du kit « Marketing » d'AI WORK KIT.
